{
  "summary": {
    "total_photos": 12,
    "invoices_ready": 2,
    "invoices_review": 1,
    "cash_orders": 3,
    "rejected_qr": 5,
    "errors": 0
  },
  "invoices": [
    {
      "group_key": "390521270428_227_2026-02-13",
      "type": "invoice",
      "status": "ready",
      "doc_type": "upd",
      "doc_number": "227",
      "date": "2026-02-13",
      "supplier": {
        "name": "ИП Рзаева Джейран Тахир Кызы",
        "inn": "390521270428"
      },
      "buyer": {
        "name": "ИП Мерзляков Егор Андреевич",
        "inn": "390511847466"
      },
      "items": [
        {
          "name": "Салат Романо вес кг",
          "unit": "кг",
          "qty": 4.0,
          "price": 285.72,
          "sum": 1142.86,
          "vat_rate": "5%"
        },
        {
          "name": "Помидор черри вес кг",
          "unit": "кг",
          "qty": 1.54,
          "price": 475.24,
          "sum": 731.87,
          "vat_rate": "5%"
        },
        {
          "name": "Морковь вес кг",
          "unit": "кг",
          "qty": 2.24,
          "price": 56.19,
          "sum": 125.87,
          "vat_rate": "5%"
        },
        {
          "name": "Петрушка вес кг",
          "unit": "кг",
          "qty": 0.54,
          "price": 333.33,
          "sum": 180.0,
          "vat_rate": "5%"
        },
        {
          "name": "Шампиньоны вес кг",
          "unit": "кг",
          "qty": 3.0,
          "price": 414.29,
          "sum": 1242.86,
          "vat_rate": "5%"
        }
      ],
      "total_amount": 3594.62,
      "item_sum": 3423.46,
      "page_count": 2,
      "total_pages": 2,
      "is_complete": true,
      "source_photos": [
        "photo_2026-02-19_06-09-31.jpg",
        "photo_2026-02-19_06-09-29.jpg"
      ],
      "confidence_score": 87,
      "warnings": []
    },
    {
      "group_key": "3900033727_38_2026-02-13",
      "type": "invoice",
      "status": "ready",
      "doc_type": "upd",
      "doc_number": "38",
      "date": "2026-02-13",
      "supplier": {
        "name": "ООО \"ПИЦЦАРЕЛЛА ТРЕЙД\"",
        "inn": "3900033727"
      },
      "buyer": {
        "name": "ИП Мерзляков Егор Андреевич",
        "inn": "390511847466"
      },
      "items": [
        {
          "name": "Сыр полутвердый \"Моцарелла Павлина\" с м.д.ж. в сухом веществе от 36 до 50%",
          "unit": "кг",
          "qty": 37.4,
          "price": 500.0,
          "sum": 18700.0,
          "vat_rate": "10%"
        }
      ],
      "total_amount": 20570.0,
      "item_sum": 18700.0,
      "page_count": 1,
      "total_pages": 1,
      "is_complete": true,
      "source_photos": [
        "photo_2026-02-19_06-09-33.jpg"
      ],
      "confidence_score": 94,
      "warnings": []
    },
    {
      "group_key": "noinn_None_None",
      "type": "invoice",
      "status": "needs_review",
      "doc_type": "other",
      "doc_number": null,
      "date": null,
      "supplier": {
        "name": "Центральный рынок",
        "inn": null
      },
      "buyer": {
        "name": "ИП Мерзликов ЕА",
        "inn": null
      },
      "items": [
        {
          "name": "лист салата",
          "unit": "гр",
          "qty": 1672.0,
          "price": null,
          "sum": 1330.0,
          "vat_rate": null
        }
      ],
      "total_amount": 1330.0,
      "item_sum": 1330.0,
      "page_count": 1,
      "total_pages": 1,
      "is_complete": true,
      "source_photos": [
        "photo_2026-02-19_06-09-45.jpg"
      ],
      "confidence_score": 70,
      "warnings": [
        "Не найден ИНН поставщика.",
        "Не найдена дата документа.",
        "Не найден номер документа."
      ]
    }
  ],
  "cash_orders": [
    {
      "type": "cash_order",
      "status": "info_only",
      "doc_type": "cash_order",
      "date": "2026-02-13",
      "supplier": {
        "name": "ИП Мерзляков ЕН",
        "inn": null
      },
      "buyer": null,
      "total_amount": 750.0,
      "items": [],
      "source_photo": "photo_2026-02-19_06-09-39.jpg",
      "message": "📋 Расходный ордер / Услуга\nДата: 2026-02-13\nОт кого: ИП Мерзляков ЕН\nКому: неизвестно\nСумма: 750.0 руб.\nЗа что: назначение не указано",
      "note": "Не подлежит импорту в iiko. Только для информации."
    },
    {
      "type": "cash_order",
      "status": "info_only",
      "doc_type": "cash_order",
      "date": "2026-02-13",
      "supplier": {
        "name": "ИП Мерзляков Е.Н.",
        "inn": null
      },
      "buyer": {
        "name": "Мерзляков Егор",
        "inn": null
      },
      "total_amount": 501.0,
      "items": [],
      "source_photo": "photo_2026-02-19_06-09-40.jpg",
      "message": "📋 Расходный ордер / Услуга\nДата: 2026-02-13\nОт кого: ИП Мерзляков Е.Н.\nКому: Мерзляков Егор\nСумма: 501.0 руб.\nЗа что: назначение не указано",
      "note": "Не подлежит импорту в iiko. Только для информации."
    },
    {
      "type": "cash_order",
      "status": "info_only",
      "doc_type": "cash_order",
      "date": "2026-02-13",
      "supplier": {
        "name": "ИП Мерзляков ЕА",
        "inn": null
      },
      "buyer": {
        "name": "Вязовой Денис",
        "inn": null
      },
      "total_amount": 4500.0,
      "items": [],
      "source_photo": "photo_2026-02-19_06-09-41.jpg",
      "message": "📋 Расходный ордер / Услуга\nДата: 2026-02-13\nОт кого: ИП Мерзляков ЕА\nКому: Вязовой Денис\nСумма: 4500.0 руб.\nЗа что: назначение не указано",
      "note": "Не подлежит импорту в iiko. Только для информации."
    }
  ],
  "rejected_qr": [
    {
      "photo": "photo_2026-02-19_06-09-32.jpg",
      "doc_number": "265",
      "date": "2026-02-13",
      "supplier": {
        "name": "ООО \"ЕВРОРИТЕЙЛ\"",
        "inn": "3906321175"
      },
      "total_amount": 1599.96,
      "reason": "Кассовый чек с QR-кодом — используйте приложение ФНС"
    },
    {
      "photo": "photo_2026-02-19_06-09-34.jpg",
      "doc_number": "125",
      "date": "2026-02-13",
      "supplier": {
        "name": "ООО \"Мариленд\"",
        "inn": "3906095286"
      },
      "total_amount": 119.98,
      "reason": "Кассовый чек с QR-кодом — используйте приложение ФНС"
    },
    {
      "photo": "photo_2026-02-19_06-09-35.jpg",
      "doc_number": "264",
      "date": "2026-02-13",
      "supplier": {
        "name": "ООО \"ЕВРОРИТЕЙЛ\"",
        "inn": "3906321175"
      },
      "total_amount": 2389.94,
      "reason": "Кассовый чек с QR-кодом — используйте приложение ФНС"
    },
    {
      "photo": "photo_2026-02-19_06-09-37.jpg",
      "doc_number": "000026009",
      "date": "2023-02-13",
      "supplier": {
        "name": "ИП Аннин Егор Ильич",
        "inn": "390514520913"
      },
      "total_amount": 10207.18,
      "reason": "Кассовый чек с QR-кодом — используйте приложение ФНС"
    },
    {
      "photo": "photo_2026-02-19_06-09-43.jpg",
      "doc_number": "2185",
      "date": "2026-02-13",
      "supplier": {
        "name": "ИП Агаев Аладдин Нуру оглы",
        "inn": "390614809381"
      },
      "total_amount": 950.0,
      "reason": "Кассовый чек с QR-кодом — используйте приложение ФНС"
    }
  ],
  "errors": []
}